ledgerx/__init__.py
ledgerx/client.py
ledgerx/trade_blotter.py
ledgerx/util.py
ledgerx/version.py
ledgerx-0.0.1.dist-info/LICENSE
ledgerx-0.0.1.dist-info/METADATA
ledgerx-0.0.1.dist-info/WHEEL
ledgerx-0.0.1.dist-info/top_level.txt
ledgerx-0.0.1.dist-info/RECORD
