Metadata-Version: 2.1
Name: ledgerx
Version: 0.0.1
Summary: python client for ledgerx
Home-page: https://github.com/westonplatter/lederx-python/
Author: Weston Platter
Author-email: westonplatter@gmail.com
License: BSD-3-Clause
Project-URL: Issue Tracker, https://github.com/westonplatter/ledgerx-python/issues
Project-URL: Source Code, https://github.com/westonplatter/ledgerx-python
Platform: UNKNOWN
Requires-Python: >=3.6
Requires-Dist: requests (>=2.20.0)
